destination_pgvector/__init__.py
destination_pgvector/common/__init__.py
destination_pgvector/common/catalog/__init__.py
destination_pgvector/common/catalog/catalog_providers.py
destination_pgvector/common/destinations/__init__.py
destination_pgvector/common/destinations/record_processor.py
destination_pgvector/common/sql/__init__.py
destination_pgvector/common/sql/sql_processor.py
destination_pgvector/common/state/__init__.py
destination_pgvector/common/state/state_writers.py
destination_pgvector/config.py
destination_pgvector/destination.py
destination_pgvector/globals.py
destination_pgvector/pgvector_processor.py
destination_pgvector/run.py
airbyte_destination_pgvector-0.1.8.dist-info/METADATA
airbyte_destination_pgvector-0.1.8.dist-info/WHEEL
airbyte_destination_pgvector-0.1.8.dist-info/entry_points.txt
airbyte_destination_pgvector-0.1.8.dist-info/RECORD
